{
  "main": {
    "id": "0f6771c55178381c",
    "type": "split",
    "children": [
      {
        "id": "a1d65b93f3896305",
        "type": "tabs",
        "children": [
          {
            "id": "53d0d203a0f1ad35",
            "type": "leaf",
            "state": {
              "type": "markdown",
              "state": {
                "file": "DevOps/flow/系统设计.md",
                "mode": "source",
                "source": false
              }
            }
          }
        ]
      }
    ],
    "direction": "vertical"
  },
  "left": {
    "id": "a65567a5e196eefa",
    "type": "split",
    "children": [
      {
        "id": "c814236f6e5ff7ec",
        "type": "tabs",
        "children": [
          {
            "id": "e94673482b6e42c1",
            "type": "leaf",
            "state": {
              "type": "file-explorer",
              "state": {
                "sortOrder": "alphabetical"
              }
            }
          },
          {
            "id": "fba8b2032d05712e",
            "type": "leaf",
            "state": {
              "type": "search",
              "state": {
                "query": "",
                "matchingCase": false,
                "explainSearch": false,
                "collapseAll": false,
                "extraContext": false,
                "sortOrder": "alphabetical"
              }
            }
          },
          {
            "id": "2b076bddb93376cf",
            "type": "leaf",
            "state": {
              "type": "bookmarks",
              "state": {}
            }
          }
        ]
      }
    ],
    "direction": "horizontal",
    "width": 200
  },
  "right": {
    "id": "d28298963bd73e59",
    "type": "split",
    "children": [
      {
        "id": "4a8ed7328191f469",
        "type": "tabs",
        "children": [
          {
            "id": "0421ca53dbc3c657",
            "type": "leaf",
            "state": {
              "type": "backlink",
              "state": {
                "file": "DevOps/flow/系统设计.md",
                "collapseAll": false,
                "extraContext": false,
                "sortOrder": "alphabetical",
                "showSearch": false,
                "searchQuery": "",
                "backlinkCollapsed": false,
                "unlinkedCollapsed": true
              }
            }
          },
          {
            "id": "7f6993b8918410aa",
            "type": "leaf",
            "state": {
              "type": "outgoing-link",
              "state": {
                "file": "DevOps/flow/系统设计.md",
                "linksCollapsed": false,
                "unlinkedCollapsed": true
              }
            }
          },
          {
            "id": "ae8a40fa129979f3",
            "type": "leaf",
            "state": {
              "type": "tag",
              "state": {
                "sortOrder": "frequency",
                "useHierarchy": true
              }
            }
          },
          {
            "id": "5be5aaa28ca4121f",
            "type": "leaf",
            "state": {
              "type": "outline",
              "state": {
                "file": "DevOps/flow/系统设计.md"
              }
            }
          },
          {
            "id": "4da76b6c3871199f",
            "type": "leaf",
            "state": {
              "type": "advanced-tables-toolbar",
              "state": {}
            }
          }
        ],
        "currentTab": 3
      }
    ],
    "direction": "horizontal",
    "width": 240.5
  },
  "left-ribbon": {
    "hiddenItems": {
      "switcher:打开快速切换": false,
      "graph:查看关系图谱": false,
      "canvas:新建白板": false,
      "daily-notes:打开/创建今天的日记": false,
      "templates:插入模板": false,
      "table-editor-obsidian:Advanced Tables Toolbar": false,
      "obsidian-excalidraw-plugin:新建绘图文件": false,
      "command-palette:打开命令面板": false
    }
  },
  "active": "53d0d203a0f1ad35",
  "lastOpenFiles": [
    "每日/2024-08-25.md",
    "DevOps/flow/系统设计.md",
    "DevOps/flow",
    "DevOps/ci/tekton.md",
    "Excalidraw/Drawing 2024-09-16 21.00.02.excalidraw.md",
    "Excalidraw/Drawing 2024-09-14 17.16.04.excalidraw.md",
    "DevOps/metrics/代码指标收集.md",
    "Excalidraw/Drawing 2024-08-16 10.18.28.excalidraw.md",
    "Excalidraw/Drawing 2024-08-16 13.30.08.excalidraw.md",
    "DevOps/ci/tekton.res/IMG-20240914175714253.png",
    "DevOps/ci/tekton.res/IMG-20240914175445117.png",
    "DevOps/ci/tekton.res/IMG-20240914170601470.png",
    "DevOps/ci/tekton.res",
    "DevOps/ci/tekton.res/IMG-20240914165750674.png",
    "基础/计算机网络/常见网络名词.md",
    "DevOps/readme.md",
    "基础/计算机网络",
    "基础",
    "DevOps/k8s/k8s 本地部署.md",
    "DevOps/metrics",
    "goc",
    "DevOps/ci/git action.md",
    "每日/2024-08-29.md",
    "中间件/clickhouse/ck数据流实时处理.md",
    "中间件/clickhouse",
    "DevOps/docker/如何选择基础镜像.res/IMG-20240825180652132.png",
    "DevOps/docker/如何选择基础镜像.res/IMG-20240825180625204.png",
    "DevOps/docker/如何选择基础镜像.res",
    "DevOps/ci/git action.res/IMG-20240825180550210.png",
    "DevOps/ci/git action.res/IMG-20240825180511306.png",
    "DevOps/ci/git action.res",
    "Pasted image 20240821195730.png",
    "Pasted image 20240821194730.png",
    "每日/2024-08-21.md",
    "DevOps/ci",
    "DevOps/docker/如何选择基础镜像.md",
    "DevOps/docker/如何提升构建速度.md",
    "最佳实践/分布式链路追踪.md",
    "DevOps/git/Git Clone.md",
    "中间件/mysql/Mysql-锁.md",
    "conflict-files-obsidian-git.md",
    "每日/2024-08-16.md",
    "README.md",
    "未命名.canvas",
    "中间件/mysql/mysql-锁.md",
    "Excalidraw/Drawing 2024-08-13 23.36.58.excalidraw.md",
    "test/README.md",
    "中间件/mysql/未命名.canvas"
  ]
}